trade.py
warmup.py
LocalTrader/__init__.py
LocalTrader/data/Data.py
LocalTrader/data/QuoteBar.py
LocalTrader/data/TradeBar.py
LocalTrader/data/resolution.py
LocalTrader/equity/equity.py
LocalTrader/files/Input.py
LocalTrader/indicators/Indicators.py
LocalTrader/sql/sql_query.py
LocalTrader/sql/sql_table.py
localtrader-0.0.1.dist-info/METADATA
localtrader-0.0.1.dist-info/WHEEL
localtrader-0.0.1.dist-info/licenses/LICENSE
localtrader-0.0.1.dist-info/RECORD
