Metadata-Version: 2.1
Name: localtrader
Version: 0.0.1
Summary: A small package for local, algorithmic trading
Project-URL: Homepage, https://github.com/slicerrr0/LocalTrader
Project-URL: Bug Tracker, https://github.com/slicerrr0/LocalTrader/issues
Author-email: slicerrr0 <mrslicerr0@protonmail.com>
License-File: LICENSE
Classifier: License :: OSI Approved :: MIT License
Classifier: Operating System :: OS Independent
Classifier: Programming Language :: Python :: 3
Requires-Python: >=3.7
